bindfit/__init__.py
bindfit/fitter.py
bindfit/functions.py
bindfit/helpers.py
bindfit-0.1.2.dist-info/METADATA
bindfit-0.1.2.dist-info/WHEEL
bindfit-0.1.2.dist-info/top_level.txt
bindfit-0.1.2.dist-info/RECORD
