Metadata-Version: 2.1
Name: bindfit
Version: 0.1.2
Summary: A binding constant fitter library for Python
Author-email: echus <varvara@echus.co>
Project-URL: Homepage, https://github.com/opendatastudio/bindfit
Project-URL: Bug Tracker, https://github.com/opendatastudio/bindfit/issues
Requires-Python: >=3.10
Requires-Dist: numpy<2.0,>=1.24.2
Requires-Dist: scipy<2.0,>=1.10.0
Requires-Dist: pandas<3.0,>=2.2
Provides-Extra: all
Requires-Dist: bindfit[development]; extra == "all"
Provides-Extra: development
Requires-Dist: pre-commit; extra == "development"
Requires-Dist: build; extra == "development"
Requires-Dist: twine; extra == "development"
